{"guide_app开发指南.md":"DlK-z9YX","guide_bsp开发指南.md":"VTsnb18J","guide_check_list.md":"DYrtdIrr","guide_drv开发指南.md":"BXyDOnxK","guide_git使用规范.md":"CsmGc82q","guide_intro.md":"B337ez2i","guide_other_cortex-m7内存使用注意事项.md":"Ciin49kh","guide_other_cubemx_freertos配置指南.md":"D2_v6ekI","guide_other_dwt使用.md":"CxZC7TkJ","guide_other_freertos静态内存api指南.md":"C9DuZ4HQ","guide_other_hal_tim_api参考.md":"CxPrxmos","guide_other_index.md":"BILfauQI","guide_other_makefile语法教程.md":"B_vtLHEN","guide_other_readelf输出文件说明.md":"Cwv9YRRE","guide_other_内存与存储原理.md":"CkmmVcXS","guide_toolchain_cmake工具链.md":"a50hWtF1","guide_toolchain_index.md":"CYlYbSr3","guide_toolchain_segger_rtt使用指南.md":"wmiAGQKS","guide_toolchain_vscode配置文件详解.md":"B34np2Ms","guide_toolchain_工具链配置.md":"Ce5E5nn1","guide_代码要求.md":"o6pSeL3W","guide_代码规范.md":"CnTr6Qfs","guide_配置文件.md":"DiNORIhq","guide_项目架构设计方案.md":"wJT7LDF9","index.md":"ByeezrpJ","manuals_bmi088.md":"CjokNR2B","manuals_c610.md":"1BcvtnGY","manuals_c620.md":"D4WHBooV","manuals_dji_a.md":"DmQm5Mil","manuals_dji_c.md":"DRed5T8f","manuals_dm4310.md":"XGWyGNaz","manuals_dm_mc02.md":"DS3PRe7z","manuals_gm6020.md":"CCa42uD6","manuals_index.md":"GGSnc4UX","manuals_ist8310.md":"C2Mq0R3u","manuals_mpu6500.md":"BNi2TLuF","public_manuals_dm_mc02_stm32h7xx参考手册v3 - dbgmcu.pdf.md":"9hXIhSOU","public_manuals_dm_mc02_stm32h7xx参考手册v3 - 复位和时钟控制.pdf.md":"BwCenWaC","public_manuals_dm_mc02_stm32h7xx参考手册v3 - 电源控制.pdf.md":"DeAa5Tdo","public_manuals_dm_mc02_stm32h7xx参考手册v3 - 通用定时器.pdf.md":"Bp_YAdMO","public_manuals_dm_mc02_stm32h7xx参考手册v3 - 高级定时器.pdf.md":"COq8mSdY"}
